{"_format":"","paths":{"artifacts":"out","build_infos":"out/build-info","sources":"src","tests":"test","scripts":"script","libraries":["lib"]},"files":{"src/REEToken.sol":{"lastModificationDate":1737186326248,"contentHash":"9e78340a92ee05ce05bf821c131fcc30","sourceName":"src/REEToken.sol","imports":[],"versionRequirement":"^0.8.0","artifacts":{"IERC20":{"0.8.25":{"default":{"path":"REEToken.sol/IERC20.json","build_id":"c6cf4a09843cd4f04ef4442c1d079172"}}},"REEToken":{"0.8.25":{"default":{"path":"REEToken.sol/REEToken.json","build_id":"c6cf4a09843cd4f04ef4442c1d079172"}}}},"seenByCompiler":true}},"builds":["c6cf4a09843cd4f04ef4442c1d079172"],"profiles":{"default":{"solc":{"optimizer":{},"metadata":{"useLiteralContent":false,"bytecodeHash":"ipfs","appendCBOR":true},"outputSelection":{"*":{"*":["abi","evm.bytecode.object","evm.bytecode.sourceMap","evm.bytecode.linkReferences","evm.deployedBytecode.object","evm.deployedBytecode.sourceMap","evm.deployedBytecode.linkReferences","evm.deployedBytecode.immutableReferences","evm.methodIdentifiers","metadata"]}},"evmVersion":"cancun","viaIR":false,"libraries":{}},"vyper":{"evmVersion":"cancun","outputSelection":{"*":{"*":["abi","evm.bytecode","evm.deployedBytecode"]}}}}}}